github_scrapper/__init__.py
github_scrapper/app/__init__.py
github_scrapper/app/git_code_scraper.py
github_scrapper/app/main.py
github_scrapper/config/__init__.py
github_scrapper/config/logging_config.py
github_scrapper-0.1.1.dist-info/LICENSE
github_scrapper-0.1.1.dist-info/METADATA
github_scrapper-0.1.1.dist-info/WHEEL
github_scrapper-0.1.1.dist-info/entry_points.txt
github_scrapper-0.1.1.dist-info/RECORD
