Metadata-Version: 2.3
Name: github-scrapper
Version: 0.1.1
Summary: A tool to scrape code from Git repositories for LLM analysis.
License: MIT
Author: Panagiotis Ioannidis
Author-email: pioannidis@pisquared.io
Requires-Python: >=3.8,<4.0
Classifier: License :: OSI Approved :: MIT License
Classifier: Programming Language :: Python :: 3
Classifier: Programming Language :: Python :: 3.8
Classifier: Programming Language :: Python :: 3.9
Classifier: Programming Language :: Python :: 3.10
Classifier: Programming Language :: Python :: 3.11
Classifier: Programming Language :: Python :: 3.12
Classifier: Programming Language :: Python :: 3.13
Requires-Dist: gitpython (>=3.1.30,<4.0.0)
Requires-Dist: requests (>=2.28.1,<3.0.0)
